.gitignore
Dockerfile
LICENSE
MANIFEST.in
README.md
alembic.ini
call_save_indices.sh
ping_clever_cloud.py
pyproject.toml
requirements.txt
save_today.py
setup.cfg
setup.py
startup.sh
wsgi.py
.github/workflows/build_publish.yml
.github/workflows/deploy.yml
indice_pollution/__init__.py
indice_pollution/_version.py
indice_pollution/api.py
indice_pollution/autocomplete.py
indice_pollution/celery_worker.py
indice_pollution/db.py
indice_pollution/extensions.py
indice_pollution/helpers.py
indice_pollution.egg-info/PKG-INFO
indice_pollution.egg-info/SOURCES.txt
indice_pollution.egg-info/dependency_links.txt
indice_pollution.egg-info/requires.txt
indice_pollution.egg-info/top_level.txt
indice_pollution/history/__init__.py
indice_pollution/history/models/__init__.py
indice_pollution/history/models/bassin_dair.py
indice_pollution/history/models/commune.py
indice_pollution/history/models/departement.py
indice_pollution/history/models/epci.py
indice_pollution/history/models/episode_pollution.py
indice_pollution/history/models/indice_atmo.py
indice_pollution/history/models/indice_uv.py
indice_pollution/history/models/potentiel_radon.py
indice_pollution/history/models/raep.py
indice_pollution/history/models/region.py
indice_pollution/history/models/tncc.py
indice_pollution/history/models/vigilance_meteo.py
indice_pollution/history/models/zone.py
indice_pollution/models/__init__.py
indice_pollution/regions/Auvergne-Rhône-Alpes.py
indice_pollution/regions/Bourgogne-Franche-Comté.py
indice_pollution/regions/Bretagne.py
indice_pollution/regions/Centre-Val de Loire.py
indice_pollution/regions/Corse.py
indice_pollution/regions/Grand Est.py
indice_pollution/regions/Guadeloupe.py
indice_pollution/regions/Guyane.py
indice_pollution/regions/Hauts-de-France.py
indice_pollution/regions/La Réunion.py
indice_pollution/regions/Martinique.py
indice_pollution/regions/Mayotte.py
indice_pollution/regions/Normandie.py
indice_pollution/regions/Nouvelle-Aquitaine.py
indice_pollution/regions/Occitanie.py
indice_pollution/regions/Pays de la Loire.py
indice_pollution/regions/Provence-Alpes-Côte d'Azur.py
indice_pollution/regions/Réunion.py
indice_pollution/regions/Sud.py
