Metadata-Version: 2.1
Name: indice-pollution
Version: 0.55.1675681085
Summary: API giving air pollution level in France
Home-page: https://github.com/l-vincent-l/indice_pollution
Author: Vincent Lara
Author-email: vincent.lara@beta.gouv.fr
License: MIT
Download-URL: https://github.com/l-vincent-l/indice_pollution/archive/0.1.2.tar.gz
Platform: UNKNOWN
Classifier: Development Status :: 3 - Alpha
Classifier: Intended Audience :: Developers
Classifier: Programming Language :: Python :: 3.8
License-File: LICENSE
